{
  "gitSyncId": "6826c5feef3662536db0ca19_1c12d8f3-35db-4fad-b709-4dacb07fe74e",
  "id": "Page1_Update_public_student_data1",
  "pluginId": "postgres-plugin",
  "pluginType": "DB",
  "unpublishedAction": {
    "actionConfiguration": {
      "body": "UPDATE public.student_data SET \"school_name\"= '{{Table1.updatedRow.school_name}}', \"class\"= '{{Table1.updatedRow.class}}', \"section\"= '{{Table1.updatedRow.section}}', \"student_name\"= '{{Table1.updatedRow.student_name}}', \"roll_number\"= '{{Table1.updatedRow.roll_number}}' WHERE \"id\"= {{Table1.updatedRow.id}};",
      "encodeParamsToggle": true,
      "paginationType": "NONE",
      "pluginSpecifiedTemplates": [
        {
          "value": false
        }
      ],
      "timeoutInMillisecond": 10000
    },
    "confirmBeforeExecute": false,
    "datasource": {
      "id": "StudentDB",
      "isAutoGenerated": false,
      "name": "StudentDB",
      "pluginId": "postgres-plugin"
    },
    "dynamicBindingPathList": [
      {
        "key": "body"
      }
    ],
    "name": "Update_public_student_data1",
    "pageId": "Page1",
    "runBehaviour": "MANUAL",
    "userSetOnLoad": false
  }
}